{
  "locale": "ru",
  "countryCode": "TUR",
  "countryName": "Турция",
  "title": "Fenerbahçe Üniversitesi",
  "description": "Частный университет в Стамбуле (Ataşehir), основан в 2016 году и связан с клубом Fenerbahçe. Быстро развивается, сочетает академическое обучение с практикой и отраслевыми партнёрствами.",
  "slug": "fenerbahce-universitesi",
  "city": "Стамбул",
  "foundedYear": 2016,
  "type": "private",
  "tuitionRange": {
    "min": 2250,
    "max": 8000,
    "currency": "USD"
  },
  "totalStudents": 8000,
  "internationalStudents": 1000,
  "hasAccommodation": true,
  "hasScholarships": true,
  "heroImage": "15f10323-a8ba-4694-a382-a763851aab15.jpg",
  "image": "bbdd25e7-015b-428a-b602-8988cf7cd75a.jpg",
  "about": {
    "history": "Основан фондом культуры, образования и здравоохранения Fenerbahçe. Университет делает ставку на современные методы обучения, практико-ориентированность и тесные связи с бизнесом, спортом и сектором здравоохранения.",
    "mission": "Готовить конкурентоспособных специалистов через сочетание академической подготовки, практики и индустриальных партнёрств, развивая сильные направления в спорте, здравоохранении, инженерии, бизнесе и коммуникациях.",
    "advantages": [
      "Современный кампус в районе Ataşehir (~100 000 м²)",
      "Партнёрства с клиниками и компаниями, стажировки для студентов",
      "Сильный спортивный компонент и развитая инфраструктура",
      "Международные обмены и сотрудничество (включая Erasmus+)",
      "Карьерный центр и поддержка трудоустройства выпускников"
    ]
  },
  "key_info_texts": {
    "city_label": "Город",
    "city_note": "район Ataşehir",
    "founded_year_label": "Год основания",
    "tuition_label": "Стоимость обучения",
    "tuition_note": "Ориентировочно; возможны скидки и гранты",
    "languages_label": "Языки обучения",
    "languages_note": "турецкий и английский",
    "total_students_label": "Студенты",
    "total_students_note": "≈ 8 000+",
    "international_students_label": "Иностранные студенты",
    "international_students_note": "1000+ из 40+ стран",
    "accommodation_label": "Проживание",
    "accommodation_note": "Общежития и партнёрские резиденции рядом",
    "type_label": "Тип университета",
    "type_note": "частный"
  },
  "campus_life": {
    "facilities": [
      {
        "name": "Библиотека",
        "description": "Современная библиотека с читальными залами и доступом к электронным ресурсам.",
        "icon": "ph:books",
        "is_active": true
      },
      {
        "name": "Лаборатории",
        "description": "Учебные и исследовательские лаборатории для инженерных и медицинских направлений.",
        "icon": "ph:flask",
        "is_active": true
      },
      {
        "name": "Спортивный центр",
        "description": "Залы, фитнес, игровые площадки, инфраструктура для спортивных программ.",
        "icon": "ph:barbell",
        "is_active": true
      },
      {
        "name": "Медицинские клиники-партнёры",
        "description": "Практика и стажировки на базе клиник и медицинских учреждений-партнёров.",
        "icon": "ph:first-aid",
        "is_active": true
      },
      {
        "name": "Общежития и резиденции",
        "description": "Общежития и партнёрские резиденции рядом с кампусом.",
        "icon": "ph:buildings",
        "is_active": true
      },
      {
        "name": "Кафе и столовые",
        "description": "Питание на кампусе, зоны отдыха и пространства для общения.",
        "icon": "ph:fork-knife",
        "is_active": true
      },
      {
        "name": "Зоны для групповой работы",
        "description": "Коворкинги, пространства для коллаборации и самостоятельной работы.",
        "icon": "ph:users-three",
        "is_active": true
      },
      {
        "name": "Высокоскоростной Wi‑Fi",
        "description": "Быстрый интернет по всему кампусу.",
        "icon": "ph:wifi-high",
        "is_active": true
      },
      {
        "name": "Студенческие клубы",
        "description": "Объединения по интересам, мероприятия и студенческие инициативы.",
        "icon": "ph:users-three",
        "is_active": true
      }
    ]
  },
  "admission": {
    "requirements": [
      {
        "category": "exam",
        "requirement": "TR-YÖS или SAT",
        "details": "Результаты приветствуются, но не всегда обязательны"
      },
      {
        "category": "language",
        "requirement": "TOEFL iBT ≥ 72 или внутренний экзамен университета",
        "details": "Для программ на английском языке"
      }
    ],
    "documents": [
      {
        "name": "Паспорт",
        "description": "Страница с данными",
        "format_requirements": [
          "скан PDF/JPEG"
        ]
      },
      {
        "name": "Аттестат о среднем образовании",
        "description": "С переводом на турецкий или английский (при необходимости)",
        "format_requirements": [
          "PDF"
        ]
      },
      {
        "name": "Выписка оценок/транскрипт",
        "description": "За все годы обучения",
        "format_requirements": [
          "PDF"
        ]
      },
      {
        "name": "Сертификат владения языком",
        "description": "TOEFL/другой сертификат или справка об уровне",
        "format_requirements": [
          "PDF"
        ]
      },
      {
        "name": "Фотография 3×4",
        "format_requirements": [
          "JPEG/PNG"
        ]
      },
      {
        "name": "Резюме (для магистратуры)",
        "format_requirements": [
          "PDF"
        ]
      }
    ],
    "scholarships": [
      {
        "name": "Скидка на обучение",
        "type": "university",
        "coverage_percentage": 55,
        "eligibility_criteria": [
          "Скидка действует на все направления обучения"
        ]
      }
    ]
  },
  "programs": [
    {
      "degree_type": "bachelor",
      "name": "Economics and Finance",
      "language": "en",
      "tuition_per_year": 4200,
      "duration_years": 4
    },
    {
      "degree_type": "bachelor",
      "name": "English Language and Literature",
      "language": "en",
      "tuition_per_year": 4200,
      "duration_years": 4
    },
    {
      "degree_type": "bachelor",
      "name": "Management Information Systems",
      "language": "en",
      "tuition_per_year": 4200,
      "duration_years": 4
    },
    {
      "degree_type": "bachelor",
      "name": "Political Science and International Relations",
      "language": "en",
      "tuition_per_year": 4200,
      "duration_years": 4
    },
    {
      "degree_type": "bachelor",
      "name": "Business Administration",
      "language": "en",
      "tuition_per_year": 4200,
      "duration_years": 4
    },
    {
      "degree_type": "bachelor",
      "name": "Psychology",
      "language": "en",
      "tuition_per_year": 4200,
      "duration_years": 4
    },
    {
      "degree_type": "bachelor",
      "name": "Psychology",
      "language": "tr",
      "tuition_per_year": 3150,
      "duration_years": 4
    },
    {
      "degree_type": "bachelor",
      "name": "Computer Engineering",
      "language": "en",
      "tuition_per_year": 4200,
      "duration_years": 4
    },
    {
      "degree_type": "bachelor",
      "name": "Software Engineering",
      "language": "en",
      "tuition_per_year": 4200,
      "duration_years": 4
    },
    {
      "degree_type": "bachelor",
      "name": "Industrial Engineering",
      "language": "en",
      "tuition_per_year": 4200,
      "duration_years": 4
    },
    {
      "degree_type": "bachelor",
      "name": "Electrical and Electronics Engineering",
      "language": "en",
      "tuition_per_year": 4200,
      "duration_years": 4
    },
    {
      "degree_type": "bachelor",
      "name": "Interior Architecture and Environmental Design",
      "language": "en",
      "tuition_per_year": 4200,
      "duration_years": 4
    },
    {
      "degree_type": "bachelor",
      "name": "Interior Architecture and Environmental Design",
      "language": "tr",
      "tuition_per_year": 3150,
      "duration_years": 4
    },
    {
      "degree_type": "bachelor",
      "name": "Architecture",
      "language": "tr",
      "tuition_per_year": 3150,
      "duration_years": 4
    },
    {
      "degree_type": "bachelor",
      "name": "New Media and Communication",
      "language": "tr",
      "tuition_per_year": 3150,
      "duration_years": 4
    },
    {
      "degree_type": "bachelor",
      "name": "Public Relations and Advertising",
      "language": "tr",
      "tuition_per_year": 3150,
      "duration_years": 4
    },
    {
      "degree_type": "bachelor",
      "name": "Radio, Television and Cinema",
      "language": "tr",
      "tuition_per_year": 3150,
      "duration_years": 4
    },
    {
      "degree_type": "bachelor",
      "name": "Occupational Therapy",
      "language": "tr",
      "tuition_per_year": 3150,
      "duration_years": 4
    },
    {
      "degree_type": "bachelor",
      "name": "Nursing",
      "language": "tr",
      "tuition_per_year": 3150,
      "duration_years": 4
    },
    {
      "degree_type": "bachelor",
      "name": "Nursing",
      "language": "en",
      "tuition_per_year": 3150,
      "duration_years": 4
    },
    {
      "degree_type": "bachelor",
      "name": "Nutrition and Dietetics",
      "language": "tr",
      "tuition_per_year": 3150,
      "duration_years": 4
    },
    {
      "degree_type": "bachelor",
      "name": "Midwifery",
      "language": "tr",
      "tuition_per_year": 3150,
      "duration_years": 4
    },
    {
      "degree_type": "bachelor",
      "name": "Physiotherapy and Rehabilitation",
      "language": "en",
      "tuition_per_year": 4200,
      "duration_years": 4
    },
    {
      "degree_type": "bachelor",
      "name": "Physiotherapy and Rehabilitation",
      "language": "tr",
      "tuition_per_year": 3150,
      "duration_years": 4
    },
    {
      "degree_type": "bachelor",
      "name": "Speech and Language Therapy",
      "language": "tr",
      "tuition_per_year": 3150,
      "duration_years": 4
    },
    {
      "degree_type": "bachelor",
      "name": "Pharmacy",
      "language": "en",
      "tuition_per_year": 8000,
      "duration_years": 5
    },
    {
      "degree_type": "bachelor",
      "name": "Pharmacy",
      "language": "tr",
      "tuition_per_year": 6500,
      "duration_years": 5
    },
    {
      "degree_type": "bachelor",
      "name": "Sport and Exercise Sciences",
      "language": "tr",
      "tuition_per_year": 3150,
      "duration_years": 4
    },
    {
      "degree_type": "bachelor",
      "name": "Physical Education and Sports",
      "language": "tr",
      "tuition_per_year": 3150,
      "duration_years": 4
    },
    {
      "degree_type": "bachelor",
      "name": "Sports Coaching",
      "language": "tr",
      "tuition_per_year": 3150,
      "duration_years": 4
    },
    {
      "degree_type": "bachelor",
      "name": "Sports Management",
      "language": "tr",
      "tuition_per_year": 3150,
      "duration_years": 4
    },
    {
      "degree_type": "master",
      "name": "MBA",
      "description": "with thesis",
      "language": "en",
      "tuition_per_year": 3300,
      "duration_years": 2
    },
    {
      "degree_type": "master",
      "name": "MBA",
      "description": "without thesis",
      "language": "en",
      "tuition_per_year": 2250,
      "duration_years": 2
    },
    {
      "degree_type": "master",
      "name": "MBA",
      "description": "with thesis",
      "language": "tr",
      "tuition_per_year": 3300,
      "duration_years": 2
    },
    {
      "degree_type": "master",
      "name": "MBA",
      "description": "without thesis",
      "language": "tr",
      "tuition_per_year": 2250,
      "duration_years": 2
    },
    {
      "degree_type": "master",
      "name": "Political Science and International Relations",
      "description": "with thesis",
      "language": "en",
      "tuition_per_year": 3300,
      "duration_years": 2
    },
    {
      "degree_type": "master",
      "name": "Political Science and International Relations",
      "description": "without thesis",
      "language": "en",
      "tuition_per_year": 2250,
      "duration_years": 2
    },
    {
      "degree_type": "master",
      "name": "Sport Sciences",
      "description": "with thesis",
      "language": "tr",
      "tuition_per_year": 3300,
      "duration_years": 2
    },
    {
      "degree_type": "master",
      "name": "Sport Sciences",
      "description": "without thesis",
      "language": "tr",
      "tuition_per_year": 2250,
      "duration_years": 2
    },
    {
      "degree_type": "master",
      "name": "Clinical Pharmacy",
      "description": "without thesis",
      "language": "tr",
      "tuition_per_year": 2250,
      "duration_years": 2
    },
    {
      "degree_type": "master",
      "name": "Internal Medicine Nursing",
      "description": "with thesis",
      "language": "tr",
      "tuition_per_year": 3300,
      "duration_years": 2
    },
    {
      "degree_type": "master",
      "name": "Organizational Behavior",
      "description": "with thesis",
      "language": "tr",
      "tuition_per_year": 3300,
      "duration_years": 2
    },
    {
      "degree_type": "master",
      "name": "Organizational Behavior",
      "description": "without thesis",
      "language": "tr",
      "tuition_per_year": 2250,
      "duration_years": 2
    }
  ]
}
