{
  "locale": "ru",
  "countryCode": "TUR",
  "countryName": "Турция",
  "title": "İstanbul Kültür Üniversitesi",
  "description": "Качественный частный университет в западной части Стамбула с широким выбором программ на английском и турецком, активной международной жизнью и гибкой системой скидок для иностранных студентов.",
  "slug": "istanbul-kultur-university",
  "city": "Стамбул",
  "foundedYear": 1997,
  "type": "private",
  "tuitionRange": {
    "min": 5950,
    "currency": "USD"
  },
  "totalStudents": 14000,
  "hasAccommodation": true,
  "hasScholarships": true,
  "heroImage": "/images/universities/kultur-bg.jpg",
  "image": "/images/universities/kultur-preview.jpg",
  "about": {
    "history": "İstanbul Kültür Üniversitesi (IKÜ) основан в 1997 году при Фонде образования Kültür College. Университет сочетает современное образование, теоретическую базу и практические навыки, ориентируясь на международные стандарты.",
    "mission": "Обеспечивать качественное образование, развивать прикладные навыки студентов и поддерживать их международную мобильность и карьерный рост.",
    "advantages": [
      "Возможность обучения на английском языке по многим программам",
      "Доступные цены относительно многих частных вузов с учётом скидок",
      "Система поддержки: языковые подготовительные курсы и офис международных студентов",
      "Широкий выбор факультетов и специальностей",
      "Участие в программах Erasmus+ и международных обменах",
      "Дополнительные скидки на обучение при высоком GPA"
    ]
  },
  "strong_programs": [
    {
      "category": "Инженерия",
      "programs": [
        "Компьютерная инженерия",
        "Программная инженерия",
        "Электротехника и электроника",
        "Промышленная инженерия",
        "Строительная инженерия"
      ]
    },
    {
      "category": "Архитектура и дизайн",
      "programs": [
        "Архитектура",
        "Дизайн интерьера и среды"
      ]
    },
    {
      "category": "Экономика и управление",
      "programs": [
        "Бизнес-администрирование",
        "Международные отношения",
        "Экономика",
        "Международная торговля и финансы"
      ]
    },
    {
      "category": "Социальные и гуманитарные науки",
      "programs": [
        "Психология",
        "Преподавание английского языка"
      ]
    },
    {
      "category": "Искусство и медиа",
      "programs": [
        "Анимация",
        "Дизайн коммуникаций",
        "Коммуникационные искусства",
        "Радио, телевидение и кино",
        "Новые медиа и коммуникации",
        "Дизайн цифровых игр"
      ]
    }
  ],
  "key_info_texts": {
    "city_label": "Город",
    "city_note": "Стамбул (европейская часть)",
    "founded_year_label": "Год основания",
    "founded_year_note": "1997",
    "tuition_label": "Стоимость",
    "tuition_note": "бакалавриат от $5,950 в год; скидки до 50%",
    "languages_label": "Языки обучения",
    "languages_note": "Турецкий, Английский",
    "total_students_label": "Студенты",
    "total_students_note": "≈14,000",
    "international_students_label": "Международные студенты",
    "international_students_note": "из 70–80 стран",
    "accommodation_label": "Проживание",
    "accommodation_note": "Студенческие общежития",
    "ranking_label": "Рейтинг",
    "ranking_text": "Хорошие позиции среди частных вузов Турции; крепкие тематические места в регионе",
    "type_label": "Тип университета",
    "type_note": "частный"
  },
  "campus_life": {
    "facilities": [
      {
        "name": "Студенческие общежития",
        "icon": "ph:bed"
      },
      {
        "name": "Библиотеки",
        "description": "Печатные и электронные ресурсы",
        "icon": "ph:books"
      },
      {
        "name": "Инженерные и дизайнерские лаборатории",
        "icon": "ph:flask"
      },
      {
        "name": "Спортивные и культурные объекты",
        "icon": "ph:barbell"
      },
      {
        "name": "Столовые и кафе",
        "icon": "ph:fork-knife"
      },
      {
        "name": "Wi‑Fi и интернет-услуги",
        "icon": "ph:wifi-high"
      },
      {
        "name": "Медицинский пункт",
        "icon": "ph:first-aid"
      },
      {
        "name": "Удобные транспортные связи",
        "icon": "ph:bus"
      },
      {
        "name": "Международный офис и Erasmus+",
        "icon": "ph:globe"
      },
      {
        "name": "Многочисленные студенческие клубы",
        "icon": "ph:users-three"
      },
      {
        "name": "Несколько кампусов (Ataköy, Şirinevler, Yeşilköy, Başakşehir)",
        "icon": "ph:buildings"
      }
    ]
  },
  "admission": {
    "requirements": [
      {
        "category": "exam",
        "requirement": "TR-YÖS или SAT",
        "details": "Не обязательны; могут потребоваться для отдельных факультетов или стипендий"
      },
      {
        "category": "language",
        "requirement": "Английский: TOEFL iBT 72+, PTE Academic 55+",
        "details": "Возможен внутренний экзамен университета или языковая подготовка"
      }
    ],
    "documents": [
      {
        "name": "Аттестат о среднем образовании",
        "description": "Апостиль и нотариальный перевод",
        "format_requirements": [
          "PDF"
        ]
      },
      {
        "name": "Заграничный паспорт",
        "description": "Срок действия не менее 2 лет",
        "format_requirements": [
          "PDF"
        ]
      },
      {
        "name": "Фотографии",
        "description": "4 шт, размер 4.5×6 см, белый фон"
      },
      {
        "name": "Denklik belgesi",
        "description": "На турецком, 100-балльная шкала",
        "format_requirements": [
          "PDF"
        ]
      }
    ],
    "scholarships": [
      {
        "name": "Скидки на обучение по успеваемости",
        "type": "university",
        "coverage_percentage": 50,
        "eligibility_criteria": [
          "Высокий GPA",
          "Результаты внутренних/внешних экзаменов"
        ]
      }
    ]
  },
  "programs": [
    {
      "degree_type": "bachelor",
      "name": "Преподавание английского языка",
      "language": "en",
      "tuition_per_year": 6900,
      "duration_years": 4
    },
    {
      "degree_type": "bachelor",
      "name": "Дошкольное образование",
      "language": "tr",
      "tuition_per_year": 5950,
      "duration_years": 4
    },
    {
      "degree_type": "bachelor",
      "name": "Психологическое консультирование и руководство",
      "language": "tr",
      "tuition_per_year": 5950,
      "duration_years": 4
    },
    {
      "degree_type": "bachelor",
      "name": "Английский язык и литература",
      "language": "en",
      "tuition_per_year": 6900,
      "duration_years": 4
    },
    {
      "degree_type": "bachelor",
      "name": "Математика и информатика",
      "language": "tr",
      "tuition_per_year": 5950,
      "duration_years": 4
    },
    {
      "degree_type": "bachelor",
      "name": "Молекулярная биология и генетика",
      "language": "tr",
      "tuition_per_year": 5950,
      "duration_years": 4
    },
    {
      "degree_type": "bachelor",
      "name": "Психология",
      "language": "tr",
      "tuition_per_year": 5950,
      "duration_years": 4
    },
    {
      "degree_type": "bachelor",
      "name": "Турецкий язык и литература",
      "language": "tr",
      "tuition_per_year": 5950,
      "duration_years": 4
    },
    {
      "degree_type": "bachelor",
      "name": "Право",
      "language": "tr",
      "tuition_per_year": 12580,
      "duration_years": 4
    },
    {
      "degree_type": "bachelor",
      "name": "Предпринимательство",
      "language": "tr",
      "tuition_per_year": 5950,
      "duration_years": 4
    },
    {
      "degree_type": "bachelor",
      "name": "Экономика",
      "language": "en",
      "tuition_per_year": 6900,
      "duration_years": 4
    },
    {
      "degree_type": "bachelor",
      "name": "Экономика",
      "language": "tr",
      "tuition_per_year": 5950,
      "duration_years": 4
    },
    {
      "degree_type": "bachelor",
      "name": "Бизнес-администрирование",
      "language": "tr",
      "tuition_per_year": 5950,
      "duration_years": 4
    },
    {
      "degree_type": "bachelor",
      "name": "Бизнес-администрирование",
      "language": "en",
      "tuition_per_year": 6900,
      "duration_years": 4
    },
    {
      "degree_type": "bachelor",
      "name": "Международные отношения",
      "language": "en",
      "tuition_per_year": 6900,
      "duration_years": 4
    },
    {
      "degree_type": "bachelor",
      "name": "Международная торговля и финансы",
      "language": "en",
      "tuition_per_year": 6900,
      "duration_years": 4
    },
    {
      "degree_type": "bachelor",
      "name": "Международная торговля и финансы",
      "language": "tr",
      "tuition_per_year": 5950,
      "duration_years": 4
    },
    {
      "degree_type": "bachelor",
      "name": "Архитектура",
      "language": "en",
      "tuition_per_year": 7500,
      "duration_years": 4
    },
    {
      "degree_type": "bachelor",
      "name": "Дизайн интерьера и среды",
      "language": "tr",
      "tuition_per_year": 5950,
      "duration_years": 4
    },
    {
      "degree_type": "bachelor",
      "name": "Дизайн интерьера и среды",
      "language": "en",
      "tuition_per_year": 7300,
      "duration_years": 4
    },
    {
      "degree_type": "bachelor",
      "name": "Компьютерная инженерия",
      "language": "en",
      "tuition_per_year": 6900,
      "duration_years": 4
    },
    {
      "degree_type": "bachelor",
      "name": "Программная инженерия",
      "language": "en",
      "tuition_per_year": 7600,
      "duration_years": 4
    },
    {
      "degree_type": "bachelor",
      "name": "Электротехника и электроника",
      "language": "en",
      "tuition_per_year": 6900,
      "duration_years": 4
    },
    {
      "degree_type": "bachelor",
      "name": "Промышленная инженерия",
      "language": "en",
      "tuition_per_year": 6900,
      "duration_years": 4
    },
    {
      "degree_type": "bachelor",
      "name": "Строительная инженерия",
      "language": "en",
      "tuition_per_year": 6900,
      "duration_years": 4
    },
    {
      "degree_type": "bachelor",
      "name": "Анимация",
      "language": "tr",
      "tuition_per_year": 5950,
      "duration_years": 4
    },
    {
      "degree_type": "bachelor",
      "name": "Дизайн коммуникаций",
      "language": "tr",
      "tuition_per_year": 5950,
      "duration_years": 4
    },
    {
      "degree_type": "bachelor",
      "name": "Коммуникационные искусства",
      "language": "tr",
      "tuition_per_year": 5950,
      "duration_years": 4
    },
    {
      "degree_type": "bachelor",
      "name": "Радио, телевидение и кино",
      "language": "tr",
      "tuition_per_year": 5950,
      "duration_years": 4
    },
    {
      "degree_type": "bachelor",
      "name": "Новые медиа и коммуникации",
      "language": "tr",
      "tuition_per_year": 5950,
      "duration_years": 4
    },
    {
      "degree_type": "bachelor",
      "name": "Дизайн цифровых игр",
      "language": "en",
      "tuition_per_year": 6900,
      "duration_years": 4
    },
    {
      "degree_type": "bachelor",
      "name": "Питание и диетология",
      "language": "tr",
      "tuition_per_year": 5950,
      "duration_years": 4
    },
    {
      "degree_type": "bachelor",
      "name": "Физиотерапия и реабилитация",
      "language": "tr",
      "tuition_per_year": 5950,
      "duration_years": 4
    },
    {
      "degree_type": "bachelor",
      "name": "Медсестринское дело",
      "language": "tr",
      "tuition_per_year": 5950,
      "duration_years": 4
    },
    {
      "degree_type": "master",
      "name": "Компьютерная инженерия",
      "language": "tr",
      "tuition_per_year": 5200,
      "duration_years": 2
    },
    {
      "degree_type": "master",
      "name": "Управление инновациями",
      "language": "tr",
      "tuition_per_year": 4000,
      "duration_years": 2
    },
    {
      "degree_type": "master",
      "name": "Управление и планирование образования",
      "language": "tr",
      "tuition_per_year": 5200,
      "duration_years": 2
    },
    {
      "degree_type": "master",
      "name": "Дошкольное образование",
      "language": "tr",
      "tuition_per_year": 5200,
      "duration_years": 2
    },
    {
      "degree_type": "master",
      "name": "Электротехника и электроника",
      "language": "tr",
      "tuition_per_year": 5200,
      "duration_years": 2
    },
    {
      "degree_type": "master",
      "name": "Инженерный менеджмент",
      "language": "tr",
      "tuition_per_year": 5200,
      "duration_years": 2
    },
    {
      "degree_type": "master",
      "name": "Инженерный менеджмент",
      "language": "en",
      "tuition_per_year": 6240,
      "duration_years": 2
    },
    {
      "degree_type": "master",
      "name": "Физика",
      "language": "tr",
      "tuition_per_year": 5200,
      "duration_years": 2
    },
    {
      "degree_type": "master",
      "name": "Дизайн интерьера и среды",
      "language": "tr",
      "tuition_per_year": 4550,
      "duration_years": 2
    },
    {
      "degree_type": "master",
      "name": "Дизайн интерьера",
      "language": "tr",
      "tuition_per_year": 6240,
      "duration_years": 2
    },
    {
      "degree_type": "master",
      "name": "Дизайн среды",
      "language": "tr",
      "tuition_per_year": 5200,
      "duration_years": 2
    },
    {
      "degree_type": "master",
      "name": "Управленческая экономика",
      "language": "tr",
      "tuition_per_year": 5200,
      "duration_years": 2
    },
    {
      "degree_type": "master",
      "name": "Денежные и капитальные рынки",
      "language": "tr",
      "tuition_per_year": 5200,
      "duration_years": 2
    },
    {
      "degree_type": "master",
      "name": "Экономика производства",
      "language": "tr",
      "tuition_per_year": 4550,
      "duration_years": 2
    },
    {
      "degree_type": "master",
      "name": "Международная экономика и финансы",
      "language": "en",
      "tuition_per_year": 6240,
      "duration_years": 2
    },
    {
      "degree_type": "master",
      "name": "Коммуникационные искусства",
      "language": "tr",
      "tuition_per_year": 5200,
      "duration_years": 2
    },
    {
      "degree_type": "master",
      "name": "Коммуникации и дизайн",
      "language": "tr",
      "tuition_per_year": 5200,
      "duration_years": 2
    },
    {
      "degree_type": "master",
      "name": "Английский язык и литература",
      "language": "en",
      "tuition_per_year": 5000,
      "duration_years": 2
    },
    {
      "degree_type": "master",
      "name": "Геотехника",
      "language": "tr",
      "tuition_per_year": 6240,
      "duration_years": 2
    },
    {
      "degree_type": "master",
      "name": "Геоматика",
      "language": "tr",
      "tuition_per_year": 5200,
      "duration_years": 2
    },
    {
      "degree_type": "master",
      "name": "Управление проектами",
      "language": "tr",
      "tuition_per_year": 5200,
      "duration_years": 2
    },
    {
      "degree_type": "master",
      "name": "Строительная инженерия",
      "language": "tr",
      "tuition_per_year": 5200,
      "duration_years": 2
    },
    {
      "degree_type": "master",
      "name": "Недвижимость и девелопмент",
      "language": "tr",
      "tuition_per_year": 5000,
      "duration_years": 2
    },
    {
      "degree_type": "master",
      "name": "Строительная инженерия",
      "language": "en",
      "tuition_per_year": 5200,
      "duration_years": 2
    },
    {
      "degree_type": "master",
      "name": "Бизнес-администрирование",
      "language": "tr",
      "tuition_per_year": 6500,
      "duration_years": 2
    },
    {
      "degree_type": "master",
      "name": "MBA",
      "language": "en",
      "tuition_per_year": 7800,
      "duration_years": 2
    },
    {
      "degree_type": "master",
      "name": "Управление качеством и производством",
      "language": "tr",
      "tuition_per_year": 5200,
      "duration_years": 2
    },
    {
      "degree_type": "master",
      "name": "Охрана труда и техника безопасности",
      "language": "tr",
      "tuition_per_year": 4680,
      "duration_years": 2
    },
    {
      "degree_type": "master",
      "name": "Менеджмент",
      "language": "tr",
      "tuition_per_year": 5200,
      "duration_years": 2
    },
    {
      "degree_type": "master",
      "name": "Публичное право",
      "language": "tr",
      "tuition_per_year": 7500,
      "duration_years": 2
    },
    {
      "degree_type": "master",
      "name": "Европейское право прав человека",
      "language": "tr",
      "tuition_per_year": 5200,
      "duration_years": 2
    },
    {
      "degree_type": "master",
      "name": "Математика и информатика",
      "language": "tr",
      "tuition_per_year": 5200,
      "duration_years": 2
    },
    {
      "degree_type": "master",
      "name": "Архитектура",
      "language": "tr",
      "tuition_per_year": 5200,
      "duration_years": 2
    },
    {
      "degree_type": "master",
      "name": "Архитектурная инженерия",
      "language": "tr",
      "tuition_per_year": 5200,
      "duration_years": 2
    },
    {
      "degree_type": "master",
      "name": "Архитектурное проектирование",
      "language": "tr",
      "tuition_per_year": 5200,
      "duration_years": 2
    },
    {
      "degree_type": "master",
      "name": "Управление строительством и технологии",
      "language": "tr",
      "tuition_per_year": 5200,
      "duration_years": 2
    },
    {
      "degree_type": "master",
      "name": "Градостроительство",
      "language": "tr",
      "tuition_per_year": 5200,
      "duration_years": 2
    },
    {
      "degree_type": "master",
      "name": "История архитектуры и реставрация",
      "language": "tr",
      "tuition_per_year": 5200,
      "duration_years": 2
    },
    {
      "degree_type": "master",
      "name": "Урбан-дизайн",
      "language": "tr",
      "tuition_per_year": 4550,
      "duration_years": 2
    },
    {
      "degree_type": "master",
      "name": "Молекулярная биология и генетика",
      "language": "tr",
      "tuition_per_year": 5200,
      "duration_years": 2
    },
    {
      "degree_type": "master",
      "name": "Частное право",
      "language": "tr",
      "tuition_per_year": 7500,
      "duration_years": 2
    },
    {
      "degree_type": "master",
      "name": "Спортивное право",
      "language": "tr",
      "tuition_per_year": 4550,
      "duration_years": 2
    },
    {
      "degree_type": "master",
      "name": "Индустриальная и организационная психология",
      "language": "tr",
      "tuition_per_year": 5200,
      "duration_years": 2
    },
    {
      "degree_type": "master",
      "name": "Клиническая психология",
      "language": "tr",
      "tuition_per_year": 13500,
      "duration_years": 2
    },
    {
      "degree_type": "master",
      "name": "Турецкий язык и литература",
      "language": "tr",
      "tuition_per_year": 5000,
      "duration_years": 2
    },
    {
      "degree_type": "master",
      "name": "Международные отношения",
      "language": "en",
      "tuition_per_year": 6240,
      "duration_years": 2
    },
    {
      "degree_type": "master",
      "name": "Европейские исследования",
      "language": "en",
      "tuition_per_year": 5200,
      "duration_years": 2
    },
    {
      "degree_type": "master",
      "name": "Физиотерапия и реабилитация",
      "language": "tr",
      "tuition_per_year": 5200,
      "duration_years": 2
    },
    {
      "degree_type": "master",
      "name": "Новые медиа и коммуникации",
      "language": "tr",
      "tuition_per_year": 5200,
      "duration_years": 2
    },
    {
      "degree_type": "master",
      "name": "Управление инновациями",
      "language": "tr",
      "tuition_per_year": 5200,
      "duration_years": 2
    },
    {
      "degree_type": "master",
      "name": "Логистика (дистанционно)",
      "language": "tr",
      "tuition_per_year": 4680,
      "duration_years": 2
    },
    {
      "degree_type": "master",
      "name": "Радио, телевидение и кино",
      "language": "tr",
      "tuition_per_year": 5200,
      "duration_years": 2
    },
    {
      "degree_type": "master",
      "name": "Арт-менеджмент",
      "language": "tr",
      "tuition_per_year": 4550,
      "duration_years": 2
    },
    {
      "degree_type": "master",
      "name": "Режиссура",
      "language": "tr",
      "tuition_per_year": 4550,
      "duration_years": 2
    }
  ]
}
